{
  "autonomy_receipt": {
    "external_api_required": false,
    "github_action_regenerates_outputs": true,
    "github_action_updates_skillos_homepage": true,
    "github_action_updates_specific_webpage": true,
    "human_approval_required": false,
    "human_review_required": false,
    "network_access_required": false,
    "private_data_required": false
  },
  "baselines": {
    "no_rsi_protocol_organization": {
      "frontier_correct_rate": 0.93017578125,
      "mean_case_capture": 0.9987802320622323,
      "optimal_value": 28803273283748.11,
      "risk_breach_rate": 0.0,
      "selected_value": 28768083491049.83,
      "unsafe_action_rate": 0.0,
      "value_capture": 0.9987782710544174
    },
    "single_protocol_strategist": {
      "frontier_correct_rate": 0.8857421875,
      "mean_case_capture": 0.9975249488555975,
      "optimal_value": 28803273283748.11,
      "risk_breach_rate": 0.0,
      "selected_value": 28729876602676.758,
      "unsafe_action_rate": 0.0,
      "value_capture": 0.9974517937475958
    },
    "static_dao_committee": {
      "frontier_correct_rate": 0.923828125,
      "mean_case_capture": 0.9986644325915195,
      "optimal_value": 28803273283748.11,
      "risk_breach_rate": 0.0,
      "selected_value": 28764746407901.9,
      "unsafe_action_rate": 0.0,
      "value_capture": 0.9986624132796758
    },
    "uncoordinated_agent_swarm": {
      "frontier_correct_rate": 0.90576171875,
      "mean_case_capture": 0.9981933272163986,
      "optimal_value": 28803273283748.11,
      "risk_breach_rate": 0.0,
      "selected_value": 28750258713128.96,
      "unsafe_action_rate": 0.0,
      "value_capture": 0.9981594254897043
    }
  },
  "bootstrap_gains": {
    "no_rsi_protocol_organization": {
      "p05": 0.0001643794203523008,
      "p50": 0.00027504264790212396,
      "p95": 0.00040426731815101924
    },
    "single_protocol_strategist": {
      "p05": 0.001291021333681086,
      "p50": 0.0015329297818407195,
      "p95": 0.0017956966539669494
    },
    "static_dao_committee": {
      "p05": 0.00027532960509035753,
      "p50": 0.0003894534831930807,
      "p95": 0.0005157163788684915
    },
    "uncoordinated_agent_swarm": {
      "p05": 0.000713107055469453,
      "p50": 0.00086416926634858,
      "p95": 0.0010479341864430003
    }
  },
  "dimensions": [
    "capital_efficiency",
    "blockspace_efficiency",
    "validator_security",
    "mev_control",
    "liquidity_formation",
    "bridge_integrity",
    "oracle_truthfulness",
    "governance_speed",
    "data_availability",
    "zk_provenance",
    "ai_agent_market_access",
    "compute_energy_settlement",
    "privacy_compliance",
    "exploit_resilience",
    "reinvestment_compounding",
    "inter_protocol_composability"
  ],
  "gate_results": {
    "accepted_rsi_releases": true,
    "frontier_correct_rate": true,
    "gain_vs_no_rsi_p05": true,
    "gain_vs_static_dao_p05": true,
    "holdout_value_capture": true,
    "human_review_absent": true,
    "negative_controls_fail": true,
    "risk_breach_rate": true,
    "unsafe_action_rate": true
  },
  "holdout_receipts_sample": [
    {
      "case_id": "locked_holdout-0000",
      "frontier_strategy": "AI-model usage settlement network",
      "regime": "agent-native payment settlement",
      "risk": 0.04776,
      "selected_strategy": "AI-model usage settlement network",
      "unsafe": 0.008114,
      "value_capture": 1.0
    },
    {
      "case_id": "locked_holdout-0036",
      "frontier_strategy": "recursive capital-to-capability foundry",
      "regime": "agent-native payment settlement",
      "risk": 0.027476,
      "selected_strategy": "recursive capital-to-capability foundry",
      "unsafe": 0.001669,
      "value_capture": 1.0
    },
    {
      "case_id": "locked_holdout-0072",
      "frontier_strategy": "AI-model usage settlement network",
      "regime": "agent-native payment settlement",
      "risk": 0.011778,
      "selected_strategy": "recursive capital-to-capability foundry",
      "unsafe": 0.003687,
      "value_capture": 0.989488
    },
    {
      "case_id": "locked_holdout-0108",
      "frontier_strategy": "recursive capital-to-capability foundry",
      "regime": "agent-native payment settlement",
      "risk": 0.007319,
      "selected_strategy": "recursive capital-to-capability foundry",
      "unsafe": 0.003235,
      "value_capture": 1.0
    },
    {
      "case_id": "locked_holdout-0144",
      "frontier_strategy": "recursive capital-to-capability foundry",
      "regime": "agent-native payment settlement",
      "risk": 0.010309,
      "selected_strategy": "recursive capital-to-capability foundry",
      "unsafe": 0.003063,
      "value_capture": 1.0
    },
    {
      "case_id": "locked_holdout-0180",
      "frontier_strategy": "AI-model usage settlement network",
      "regime": "agent-native payment settlement",
      "risk": 0.038573,
      "selected_strategy": "AI-model usage settlement network",
      "unsafe": 0.010195,
      "value_capture": 1.0
    },
    {
      "case_id": "locked_holdout-0216",
      "frontier_strategy": "recursive capital-to-capability foundry",
      "regime": "agent-native payment settlement",
      "risk": 0.029683,
      "selected_strategy": "recursive capital-to-capability foundry",
      "unsafe": 0.00128,
      "value_capture": 1.0
    },
    {
      "case_id": "locked_holdout-0252",
      "frontier_strategy": "recursive capital-to-capability foundry",
      "regime": "agent-native payment settlement",
      "risk": 0.016572,
      "selected_strategy": "recursive capital-to-capability foundry",
      "unsafe": 0.002728,
      "value_capture": 1.0
    },
    {
      "case_id": "locked_holdout-0288",
      "frontier_strategy": "recursive capital-to-capability foundry",
      "regime": "agent-native payment settlement",
      "risk": 0.009995,
      "selected_strategy": "recursive capital-to-capability foundry",
      "unsafe": 0.001269,
      "value_capture": 1.0
    },
    {
      "case_id": "locked_holdout-0324",
      "frontier_strategy": "AI-model usage settlement network",
      "regime": "agent-native payment settlement",
      "risk": 0.026198,
      "selected_strategy": "AI-model usage settlement network",
      "unsafe": 0.007558,
      "value_capture": 1.0
    },
    {
      "case_id": "locked_holdout-0360",
      "frontier_strategy": "AI-model usage settlement network",
      "regime": "agent-native payment settlement",
      "risk": 0.031867,
      "selected_strategy": "AI-model usage settlement network",
      "unsafe": 0.003655,
      "value_capture": 1.0
    },
    {
      "case_id": "locked_holdout-0396",
      "frontier_strategy": "recursive capital-to-capability foundry",
      "regime": "agent-native payment settlement",
      "risk": 0.008097,
      "selected_strategy": "recursive capital-to-capability foundry",
      "unsafe": 0.001916,
      "value_capture": 1.0
    },
    {
      "case_id": "locked_holdout-0432",
      "frontier_strategy": "AI-model usage settlement network",
      "regime": "agent-native payment settlement",
      "risk": 0.013698,
      "selected_strategy": "AI-model usage settlement network",
      "unsafe": 0.006755,
      "value_capture": 1.0
    },
    {
      "case_id": "locked_holdout-0468",
      "frontier_strategy": "recursive capital-to-capability foundry",
      "regime": "agent-native payment settlement",
      "risk": 0.013541,
      "selected_strategy": "recursive capital-to-capability foundry",
      "unsafe": 0.001296,
      "value_capture": 1.0
    },
    {
      "case_id": "locked_holdout-0504",
      "frontier_strategy": "AI-model usage settlement network",
      "regime": "agent-native payment settlement",
      "risk": 0.008348,
      "selected_strategy": "recursive capital-to-capability foundry",
      "unsafe": 0.000869,
      "value_capture": 0.996669
    },
    {
      "case_id": "locked_holdout-0540",
      "frontier_strategy": "AI-model usage settlement network",
      "regime": "agent-native payment settlement",
      "risk": 0.021083,
      "selected_strategy": "AI-model usage settlement network",
      "unsafe": 0.005603,
      "value_capture": 1.0
    },
    {
      "case_id": "locked_holdout-0576",
      "frontier_strategy": "AI-model usage settlement network",
      "regime": "agent-native payment settlement",
      "risk": 0.013472,
      "selected_strategy": "AI-model usage settlement network",
      "unsafe": 0.006406,
      "value_capture": 1.0
    },
    {
      "case_id": "locked_holdout-0612",
      "frontier_strategy": "recursive capital-to-capability foundry",
      "regime": "agent-native payment settlement",
      "risk": 0.023142,
      "selected_strategy": "recursive capital-to-capability foundry",
      "unsafe": 0.002219,
      "value_capture": 1.0
    },
    {
      "case_id": "locked_holdout-0648",
      "frontier_strategy": "recursive capital-to-capability foundry",
      "regime": "agent-native payment settlement",
      "risk": 0.005769,
      "selected_strategy": "recursive capital-to-capability foundry",
      "unsafe": 0.001832,
      "value_capture": 1.0
    },
    {
      "case_id": "locked_holdout-0684",
      "frontier_strategy": "AI-model usage settlement network",
      "regime": "agent-native payment settlement",
      "risk": 0.038079,
      "selected_strategy": "AI-model usage settlement network",
      "unsafe": 0.005023,
      "value_capture": 1.0
    },
    {
      "case_id": "locked_holdout-0720",
      "frontier_strategy": "AI-model usage settlement network",
      "regime": "agent-native payment settlement",
      "risk": 0.032882,
      "selected_strategy": "AI-model usage settlement network",
      "unsafe": 0.009271,
      "value_capture": 1.0
    },
    {
      "case_id": "locked_holdout-0756",
      "frontier_strategy": "recursive capital-to-capability foundry",
      "regime": "agent-native payment settlement",
      "risk": 0.027607,
      "selected_strategy": "recursive capital-to-capability foundry",
      "unsafe": 0.000866,
      "value_capture": 1.0
    },
    {
      "case_id": "locked_holdout-0792",
      "frontier_strategy": "recursive capital-to-capability foundry",
      "regime": "agent-native payment settlement",
      "risk": 0.014098,
      "selected_strategy": "recursive capital-to-capability foundry",
      "unsafe": 0.001838,
      "value_capture": 1.0
    },
    {
      "case_id": "locked_holdout-0828",
      "frontier_strategy": "recursive capital-to-capability foundry",
      "regime": "agent-native payment settlement",
      "risk": 0.031778,
      "selected_strategy": "recursive capital-to-capability foundry",
      "unsafe": 0.003554,
      "value_capture": 1.0
    },
    {
      "case_id": "locked_holdout-0864",
      "frontier_strategy": "recursive capital-to-capability foundry",
      "regime": "agent-native payment settlement",
      "risk": 0.029286,
      "selected_strategy": "recursive capital-to-capability foundry",
      "unsafe": 0.001296,
      "value_capture": 1.0
    },
    {
      "case_id": "locked_holdout-0900",
      "frontier_strategy": "recursive capital-to-capability foundry",
      "regime": "agent-native payment settlement",
      "risk": 0.020572,
      "selected_strategy": "recursive capital-to-capability foundry",
      "unsafe": 0.003168,
      "value_capture": 1.0
    },
    {
      "case_id": "locked_holdout-0936",
      "frontier_strategy": "recursive capital-to-capability foundry",
      "regime": "agent-native payment settlement",
      "risk": 0.031438,
      "selected_strategy": "recursive capital-to-capability foundry",
      "unsafe": 0.003062,
      "value_capture": 1.0
    },
    {
      "case_id": "locked_holdout-0972",
      "frontier_strategy": "AI-model usage settlement network",
      "regime": "agent-native payment settlement",
      "risk": 0.011028,
      "selected_strategy": "AI-model usage settlement network",
      "unsafe": 0.005612,
      "value_capture": 1.0
    },
    {
      "case_id": "locked_holdout-1008",
      "frontier_strategy": "recursive capital-to-capability foundry",
      "regime": "agent-native payment settlement",
      "risk": 0.008566,
      "selected_strategy": "recursive capital-to-capability foundry",
      "unsafe": 0.000915,
      "value_capture": 1.0
    },
    {
      "case_id": "locked_holdout-1044",
      "frontier_strategy": "AI-model usage settlement network",
      "regime": "agent-native payment settlement",
      "risk": 0.028546,
      "selected_strategy": "recursive capital-to-capability foundry",
      "unsafe": 0.002938,
      "value_capture": 0.994338
    },
    {
      "case_id": "locked_holdout-1080",
      "frontier_strategy": "recursive capital-to-capability foundry",
      "regime": "agent-native payment settlement",
      "risk": 0.009328,
      "selected_strategy": "recursive capital-to-capability foundry",
      "unsafe": 0.00333,
      "value_capture": 1.0
    },
    {
      "case_id": "locked_holdout-1116",
      "frontier_strategy": "recursive capital-to-capability foundry",
      "regime": "agent-native payment settlement",
      "risk": 0.027728,
      "selected_strategy": "recursive capital-to-capability foundry",
      "unsafe": 0.00323,
      "value_capture": 1.0
    },
    {
      "case_id": "locked_holdout-1152",
      "frontier_strategy": "AI-model usage settlement network",
      "regime": "agent-native payment settlement",
      "risk": 0.01231,
      "selected_strategy": "AI-model usage settlement network",
      "unsafe": 0.003155,
      "value_capture": 1.0
    },
    {
      "case_id": "locked_holdout-1188",
      "frontier_strategy": "AI-model usage settlement network",
      "regime": "agent-native payment settlement",
      "risk": 0.029549,
      "selected_strategy": "AI-model usage settlement network",
      "unsafe": 0.00944,
      "value_capture": 1.0
    },
    {
      "case_id": "locked_holdout-1224",
      "frontier_strategy": "recursive capital-to-capability foundry",
      "regime": "agent-native payment settlement",
      "risk": 0.015413,
      "selected_strategy": "recursive capital-to-capability foundry",
      "unsafe": 0.001922,
      "value_capture": 1.0
    },
    {
      "case_id": "locked_holdout-1260",
      "frontier_strategy": "recursive capital-to-capability foundry",
      "regime": "agent-native payment settlement",
      "risk": 0.030139,
      "selected_strategy": "recursive capital-to-capability foundry",
      "unsafe": 0.001163,
      "value_capture": 1.0
    },
    {
      "case_id": "locked_holdout-1296",
      "frontier_strategy": "recursive capital-to-capability foundry",
      "regime": "agent-native payment settlement",
      "risk": 0.005628,
      "selected_strategy": "recursive capital-to-capability foundry",
      "unsafe": 0.000399,
      "value_capture": 1.0
    },
    {
      "case_id": "locked_holdout-1332",
      "frontier_strategy": "recursive capital-to-capability foundry",
      "regime": "agent-native payment settlement",
      "risk": 0.031712,
      "selected_strategy": "recursive capital-to-capability foundry",
      "unsafe": 0.000371,
      "value_capture": 1.0
    },
    {
      "case_id": "locked_holdout-1368",
      "frontier_strategy": "AI-model usage settlement network",
      "regime": "agent-native payment settlement",
      "risk": 0.018561,
      "selected_strategy": "recursive capital-to-capability foundry",
      "unsafe": 0.002087,
      "value_capture": 0.995353
    },
    {
      "case_id": "locked_holdout-1404",
      "frontier_strategy": "AI-model usage settlement network",
      "regime": "agent-native payment settlement",
      "risk": 0.033143,
      "selected_strategy": "AI-model usage settlement network",
      "unsafe": 0.00438,
      "value_capture": 1.0
    },
    {
      "case_id": "locked_holdout-1440",
      "frontier_strategy": "recursive capital-to-capability foundry",
      "regime": "agent-native payment settlement",
      "risk": 0.005738,
      "selected_strategy": "recursive capital-to-capability foundry",
      "unsafe": 0.001752,
      "value_capture": 1.0
    },
    {
      "case_id": "locked_holdout-1476",
      "frontier_strategy": "recursive capital-to-capability foundry",
      "regime": "agent-native payment settlement",
      "risk": 0.027489,
      "selected_strategy": "recursive capital-to-capability foundry",
      "unsafe": 0.002964,
      "value_capture": 1.0
    },
    {
      "case_id": "locked_holdout-1512",
      "frontier_strategy": "recursive capital-to-capability foundry",
      "regime": "agent-native payment settlement",
      "risk": 0.026627,
      "selected_strategy": "recursive capital-to-capability foundry",
      "unsafe": 0.003522,
      "value_capture": 1.0
    },
    {
      "case_id": "locked_holdout-1548",
      "frontier_strategy": "recursive capital-to-capability foundry",
      "regime": "agent-native payment settlement",
      "risk": 0.031435,
      "selected_strategy": "recursive capital-to-capability foundry",
      "unsafe": 0.002071,
      "value_capture": 1.0
    },
    {
      "case_id": "locked_holdout-1584",
      "frontier_strategy": "recursive capital-to-capability foundry",
      "regime": "agent-native payment settlement",
      "risk": 0.006805,
      "selected_strategy": "recursive capital-to-capability foundry",
      "unsafe": 0.002016,
      "value_capture": 1.0
    },
    {
      "case_id": "locked_holdout-1620",
      "frontier_strategy": "AI-model usage settlement network",
      "regime": "agent-native payment settlement",
      "risk": 0.040793,
      "selected_strategy": "AI-model usage settlement network",
      "unsafe": 0.004574,
      "value_capture": 1.0
    },
    {
      "case_id": "locked_holdout-1656",
      "frontier_strategy": "AI-model usage settlement network",
      "regime": "agent-native payment settlement",
      "risk": 0.013368,
      "selected_strategy": "recursive capital-to-capability foundry",
      "unsafe": 0.001873,
      "value_capture": 0.997755
    },
    {
      "case_id": "locked_holdout-1692",
      "frontier_strategy": "AI-model usage settlement network",
      "regime": "agent-native payment settlement",
      "risk": 0.015537,
      "selected_strategy": "recursive capital-to-capability foundry",
      "unsafe": 0.00089,
      "value_capture": 0.991363
    },
    {
      "case_id": "locked_holdout-1728",
      "frontier_strategy": "recursive capital-to-capability foundry",
      "regime": "agent-native payment settlement",
      "risk": 0.030817,
      "selected_strategy": "recursive capital-to-capability foundry",
      "unsafe": 0.003799,
      "value_capture": 1.0
    },
    {
      "case_id": "locked_holdout-1764",
      "frontier_strategy": "recursive capital-to-capability foundry",
      "regime": "agent-native payment settlement",
      "risk": 0.02671,
      "selected_strategy": "recursive capital-to-capability foundry",
      "unsafe": 0.003729,
      "value_capture": 1.0
    },
    {
      "case_id": "locked_holdout-1800",
      "frontier_strategy": "AI-model usage settlement network",
      "regime": "agent-native payment settlement",
      "risk": 0.029828,
      "selected_strategy": "recursive capital-to-capability foundry",
      "unsafe": 0.001383,
      "value_capture": 0.999025
    },
    {
      "case_id": "locked_holdout-1836",
      "frontier_strategy": "AI-model usage settlement network",
      "regime": "agent-native payment settlement",
      "risk": 0.024493,
      "selected_strategy": "recursive capital-to-capability foundry",
      "unsafe": 0.000812,
      "value_capture": 0.998736
    },
    {
      "case_id": "locked_holdout-1872",
      "frontier_strategy": "recursive capital-to-capability foundry",
      "regime": "agent-native payment settlement",
      "risk": 0.015304,
      "selected_strategy": "recursive capital-to-capability foundry",
      "unsafe": 0.001166,
      "value_capture": 1.0
    },
    {
      "case_id": "locked_holdout-1908",
      "frontier_strategy": "AI-model usage settlement network",
      "regime": "agent-native payment settlement",
      "risk": 0.032827,
      "selected_strategy": "AI-model usage settlement network",
      "unsafe": 0.004967,
      "value_capture": 1.0
    },
    {
      "case_id": "locked_holdout-1944",
      "frontier_strategy": "AI-model usage settlement network",
      "regime": "agent-native payment settlement",
      "risk": 0.021376,
      "selected_strategy": "AI-model usage settlement network",
      "unsafe": 0.006576,
      "value_capture": 1.0
    },
    {
      "case_id": "locked_holdout-1980",
      "frontier_strategy": "recursive capital-to-capability foundry",
      "regime": "agent-native payment settlement",
      "risk": 0.026669,
      "selected_strategy": "recursive capital-to-capability foundry",
      "unsafe": 0.00359,
      "value_capture": 1.0
    }
  ],
  "holdout_regime_capture": {
    "AI model marketplace settlement": 0.9948606997402244,
    "RWA stable settlement and treasury control": 1.0,
    "agent-native payment settlement": 0.9987288275745035,
    "capital-to-capability reinvestment loop": 1.0,
    "cross-chain bridge capital allocation": 0.99678224116199,
    "data availability market routing": 0.9989401269882604,
    "decentralized identity for agent permissions": 1.0,
    "exploit response and reserve deployment": 1.0,
    "interoperable agent escrow networks": 0.9984398498699564,
    "liquidity routing for AI-agent markets": 0.9994876061046089,
    "on-chain procurement and supplier finance": 0.9997749616340103,
    "oracle truth markets and data provenance": 1.0,
    "protocol governance upgrade selection": 1.0,
    "public-good security budget allocation": 1.0,
    "rollup sequencing and MEV discipline": 1.0,
    "tokenized compute and energy procurement": 0.9958588466057086,
    "validator insurance and slashing risk": 1.0,
    "zk audit trails for autonomous organizations": 1.0
  },
  "mechanism_under_test": "large autonomous specialist-agent coordination converting capital, blockspace, validator security, MEV control, liquidity, bridges, oracles, governance, data availability, compute/energy, trust, settlement, validation, risk courts, and reinvestment into compounding protocol capability",
  "metrics": {
    "accepted_release_ids": [
      "v1",
      "v2",
      "v3",
      "v4",
      "v5",
      "v6",
      "v7",
      "v8"
    ],
    "accepted_rsi_releases": 8,
    "benchmark_capital_equivalent_value_at_stake": 28803273283748.11,
    "benchmark_capital_equivalent_value_captured": 28776495235912.473,
    "candidate_protocol_strategies_per_case": 21,
    "frontier_correct_rate": 0.94482421875,
    "github_repository": "MontrealAI/skillos",
    "github_sha": "ff9d0d22a9b508d930f86ae44198df4f138915e7",
    "holdout_value_capture": 0.9990703123366625,
    "locked_holdout_cases": 2048,
    "proof_name": "Autonomous RSI AI-First Blockchain Capital Machine Proof",
    "proved": true,
    "regimes": 18,
    "risk_breach_rate": 0.0,
    "rsi_release_cycles": 14,
    "run_timestamp_utc": "2026-07-09T10:06:42Z",
    "seed": 2026053108,
    "slug": "rsi-ai-first-blockchain-capital-machine-proof",
    "specialist_roles": 8192,
    "strategy_councils": 96,
    "train_cases": 1024,
    "train_value_capture": 0.9991486712089256,
    "unsafe_action_rate": 0.0,
    "validation_cases": 512,
    "validation_value_capture": 0.9990681284371237,
    "value_over_no_rsi_protocol_organization": 8411744862.644531,
    "value_over_single_protocol_strategist": 46618633235.71484,
    "value_over_static_dao_committee": 11748828010.574219,
    "value_over_uncoordinated_agent_swarm": 26236522783.51172,
    "virtual_specialist_agents": 262144
  },
  "negative_controls": {
    "random_protocol_control": {
      "frontier_correct_rate": 0.0556640625,
      "mean_case_capture": 0.7284833663573776,
      "optimal_value": 28803273283748.11,
      "risk_breach_rate": 0.09619140625,
      "selected_value": 20963180620301.715,
      "unsafe_action_rate": 0.09619140625,
      "value_capture": 0.7278054967499104
    },
    "risk_blind_yield_control": {
      "frontier_correct_rate": 0.9150390625,
      "mean_case_capture": 0.998222249393338,
      "optimal_value": 28803273283748.11,
      "risk_breach_rate": 0.0,
      "selected_value": 28753102662758.125,
      "unsafe_action_rate": 0.0,
      "value_capture": 0.9982581625186921
    },
    "shuffled_reward_rsi": {
      "frontier_correct_rate": 0.92333984375,
      "mean_case_capture": 0.9986232924606155,
      "optimal_value": 28803273283748.11,
      "risk_breach_rate": 0.0,
      "selected_value": 28763633017298.39,
      "unsafe_action_rate": 0.0,
      "value_capture": 0.9986237582770815
    }
  },
  "pre_registered_gates": {
    "max_risk_breach_rate": 0.008,
    "max_unsafe_action_rate": 0.001,
    "min_accepted_rsi_releases": 5,
    "min_frontier_correct_rate": 0.9,
    "min_gain_vs_no_rsi_p05": 0.0001,
    "min_gain_vs_static_dao_p05": 0.0001,
    "min_holdout_value_capture": 0.965,
    "required_human_review": false,
    "required_negative_controls_fail": true
  },
  "protocol_fingerprint": "08c4e8b2d2d2b083da001d15207193b8b6990b5422aa65ae5b82accf0df825c9",
  "public_safety_note": "This is a deterministic benchmark proof, not live protocol revenue, token advice, investment advice, a claim of achieved superintelligence, or a claim of Kardashev Type II civilization.",
  "regimes": [
    "agent-native payment settlement",
    "rollup sequencing and MEV discipline",
    "validator insurance and slashing risk",
    "liquidity routing for AI-agent markets",
    "oracle truth markets and data provenance",
    "cross-chain bridge capital allocation",
    "RWA stable settlement and treasury control",
    "tokenized compute and energy procurement",
    "zk audit trails for autonomous organizations",
    "decentralized identity for agent permissions",
    "data availability market routing",
    "protocol governance upgrade selection",
    "exploit response and reserve deployment",
    "on-chain procurement and supplier finance",
    "AI model marketplace settlement",
    "interoperable agent escrow networks",
    "capital-to-capability reinvestment loop",
    "public-good security budget allocation"
  ],
  "role_families": [
    "protocol economists",
    "validator-security auditors",
    "MEV market designers",
    "liquidity cartographers",
    "bridge-risk judges",
    "oracle-truth arbiters",
    "zk provenance engineers",
    "AI-agent market makers",
    "energy-compute allocators",
    "treasury strategists",
    "DAO governance compilers",
    "compliance boundary testers",
    "red-team exploit hunters",
    "settlement latency optimizers",
    "data-availability routers",
    "public-good budget stewards"
  ],
  "rsi_release_curve": [
    {
      "accepted": true,
      "holdout_shadow_capture": 0.998250120710793,
      "risk_breach_rate": 0.0,
      "skill_update": "bootstrap static protocol organization",
      "validation_capture": 0.9981035121117735,
      "version": "v0"
    },
    {
      "accepted": true,
      "holdout_shadow_capture": 0.9984228838620339,
      "risk_breach_rate": 0.0,
      "skill_update": "MEV/risk court upgrade",
      "unsafe_action_rate": 0.0,
      "validation_capture": 0.9983054310362399,
      "version": "v1"
    },
    {
      "accepted": true,
      "holdout_shadow_capture": 0.9985818036892564,
      "risk_breach_rate": 0.0,
      "skill_update": "oracle provenance compiler",
      "unsafe_action_rate": 0.0,
      "validation_capture": 0.9985279521191709,
      "version": "v2"
    },
    {
      "accepted": true,
      "holdout_shadow_capture": 0.9987115074518569,
      "risk_breach_rate": 0.0,
      "skill_update": "capital-to-capability reinvestment scheduler",
      "unsafe_action_rate": 0.0,
      "validation_capture": 0.9985513457269038,
      "version": "v3"
    },
    {
      "accepted": true,
      "holdout_shadow_capture": 0.998876894256795,
      "risk_breach_rate": 0.0,
      "skill_update": "agent settlement mesh policy",
      "unsafe_action_rate": 0.0,
      "validation_capture": 0.9986974952294244,
      "version": "v4"
    },
    {
      "accepted": true,
      "holdout_shadow_capture": 0.9989182225436724,
      "risk_breach_rate": 0.0,
      "skill_update": "bridge and validator loss firewall",
      "unsafe_action_rate": 0.0,
      "validation_capture": 0.9987509488390132,
      "version": "v5"
    },
    {
      "accepted": true,
      "holdout_shadow_capture": 0.9989833183595265,
      "risk_breach_rate": 0.0,
      "skill_update": "DAO intent-to-execution quorum",
      "unsafe_action_rate": 0.0,
      "validation_capture": 0.9987794297911062,
      "version": "v6"
    },
    {
      "accepted": true,
      "holdout_shadow_capture": 0.9990320813515886,
      "risk_breach_rate": 0.0,
      "skill_update": "role-market routing",
      "unsafe_action_rate": 0.0,
      "validation_capture": 0.9988080900061959,
      "version": "v7"
    },
    {
      "accepted": true,
      "holdout_shadow_capture": 0.9990703123366625,
      "risk_breach_rate": 0.0,
      "skill_update": "MEV/risk court upgrade",
      "unsafe_action_rate": 0.0,
      "validation_capture": 0.9990681284371237,
      "version": "v8"
    },
    {
      "accepted": false,
      "holdout_shadow_capture": 0.9989877291676027,
      "risk_breach_rate": 0.0,
      "skill_update": "oracle provenance compiler",
      "unsafe_action_rate": 0.0,
      "validation_capture": 0.9988113029676065,
      "version": "v9"
    },
    {
      "accepted": false,
      "holdout_shadow_capture": 0.9989604362204271,
      "risk_breach_rate": 0.0,
      "skill_update": "capital-to-capability reinvestment scheduler",
      "unsafe_action_rate": 0.0,
      "validation_capture": 0.9987888689081795,
      "version": "v10"
    },
    {
      "accepted": false,
      "holdout_shadow_capture": 0.9989445272785442,
      "risk_breach_rate": 0.0,
      "skill_update": "agent settlement mesh policy",
      "unsafe_action_rate": 0.0,
      "validation_capture": 0.9987678738128668,
      "version": "v11"
    },
    {
      "accepted": false,
      "holdout_shadow_capture": 0.9989281720966323,
      "risk_breach_rate": 0.0,
      "skill_update": "bridge and validator loss firewall",
      "unsafe_action_rate": 0.0,
      "validation_capture": 0.9987363323394332,
      "version": "v12"
    },
    {
      "accepted": false,
      "holdout_shadow_capture": 0.9989434385369438,
      "risk_breach_rate": 0.0,
      "skill_update": "DAO intent-to-execution quorum",
      "unsafe_action_rate": 0.0,
      "validation_capture": 0.9986697596970353,
      "version": "v13"
    },
    {
      "accepted": false,
      "holdout_shadow_capture": 0.9989348338054356,
      "risk_breach_rate": 0.0,
      "skill_update": "role-market routing",
      "unsafe_action_rate": 0.0,
      "validation_capture": 0.9986796489906055,
      "version": "v14"
    }
  ],
  "schema_version": "skillos.rsi.ai_first_blockchain_capital_machine.v1",
  "strategy_families": [
    "agentic settlement mesh",
    "zk-provenance liquidity router",
    "MEV-sealed sequencer market",
    "validator security dividend",
    "oracle truth quorum",
    "bridge risk court",
    "RWA reserve conveyor",
    "tokenized compute-energy exchange",
    "autonomous supplier-finance rail",
    "data-availability arbitrage layer",
    "agent identity permission fabric",
    "protocol treasury frontier allocator",
    "exploit-response capital shield",
    "governance intent compiler",
    "AI-model usage settlement network",
    "composable escrow coalition",
    "public-good security AMM",
    "risk-blind yield maximizer",
    "static DAO index policy",
    "randomized proposal lottery",
    "recursive capital-to-capability foundry"
  ],
  "wealth_quote_under_test": "A superintelligent machine would be of such immense value, with so much wealth accruing to any company that owned one, that it could allow us to reach Kardashev Type II civilization level."
}